aioruuvigateway/__about__.py
aioruuvigateway/__init__.py
aioruuvigateway/__main__.py
aioruuvigateway/api.py
aioruuvigateway/excs.py
aioruuvigateway/models.py
aioruuvigateway/py.typed
aioruuvigateway-0.0.2.dist-info/METADATA
aioruuvigateway-0.0.2.dist-info/WHEEL
aioruuvigateway-0.0.2.dist-info/licenses/LICENSE.txt
aioruuvigateway-0.0.2.dist-info/RECORD
