Metadata-Version: 2.1
Name: aioruuvigateway
Version: 0.0.2
Project-URL: Documentation, https://github.com/unknown/aioruuvigateway#readme
Project-URL: Issues, https://github.com/unknown/aioruuvigateway/issues
Project-URL: Source, https://github.com/unknown/aioruuvigateway
Author-email: Aarni Koskela <akx@iki.fi>
License-Expression: MIT
License-File: LICENSE.txt
Classifier: Development Status :: 4 - Beta
Classifier: Programming Language :: Python
Classifier: Programming Language :: Python :: 3.7
Classifier: Programming Language :: Python :: 3.8
Classifier: Programming Language :: Python :: 3.9
Classifier: Programming Language :: Python :: 3.10
Classifier: Programming Language :: Python :: 3.11
Classifier: Programming Language :: Python :: Implementation :: CPython
Classifier: Programming Language :: Python :: Implementation :: PyPy
Requires-Python: >=3.7
Requires-Dist: bluetooth-data-tools~=0.3.1
Requires-Dist: httpx>=0.23.0
